stockait/__init__.py
stockait/dataLoad.py
stockait/dataPreprocessing.py
stockait/simulation.py
stockait/trader.py
stockait/training.py
stockait-1.0.0.dist-info/LICENSE.md
stockait-1.0.0.dist-info/METADATA
stockait-1.0.0.dist-info/WHEEL
stockait-1.0.0.dist-info/top_level.txt
stockait-1.0.0.dist-info/RECORD
