Metadata-Version: 2.1
Name: stockait
Version: 1.0.0
Summary: Make your stock investment smarter, join StockAit!
Home-page: https://github.com/stockAI-py/stockait
Author: Eunsu Kim, Sieun Kim, Eunji Cha, Yujin Cha
Author-email: stockai2023@gmail.com
Classifier: Programming Language :: Python :: 3
Classifier: License :: OSI Approved :: MIT License
Classifier: Operating System :: OS Independent
Requires-Python: >=3.6
License-File: LICENSE.md
Requires-Dist: numpy
Requires-Dist: pandas
Requires-Dist: tqdm
Requires-Dist: yfinance
Requires-Dist: xgboost
Requires-Dist: lightgbm
Requires-Dist: ta
Requires-Dist: matplotlib
Requires-Dist: sklearn
Requires-Dist: seaborn
Requires-Dist: boto3
Requires-Dist: sqlalchemy
Requires-Dist: pymysql
